[
    {
        "ParameterKey": "AvailabilityZones",
        "ParameterValue": "$[taskcat_getaz_2]"
    },
    {
        "ParameterKey": "EmailAddress",
        "ParameterValue": "veronica.munoz@wizeline.com"
    },
    {
        "ParameterKey": "KeyPairName",
        "ParameterValue": "arn:aws:iam::609609837128:user/vero-wizeline"
    },
    {
        "ParameterKey": "WebserverCIDR",
        "ParameterValue": "0.0.0.0/0"
    },
    {
        "ParameterKey": "QSS3KeyPrefix",
        "ParameterValue": "qs-workshop/"
    },
    {
        "ParameterKey": "QSS3BucketName",
        "ParameterValue": "$[taskcat_autobucket]"
    }
]
